dblinker/__init__.py
dblinker/app_settings.yaml
dblinker/dbconfig_manager.py
dblinker/settings_loader.py
dblinker/sqlite2pg.py
dblinker/common/__init__.py
dblinker/common/config/__init__.py
dblinker/common/templates/postgres.yaml
dblinker/common/templates/sqlite.yaml
dblinker/common/utils/__init__.py
dblinker/connections/__init__.py
dblinker/connections/base.py
dblinker/connections/postgres/__init__.py
dblinker/connections/postgres/async_connection.py
dblinker/connections/postgres/async_pool_connection.py
dblinker/connections/postgres/base_connection.py
dblinker/connections/postgres/normal_connection.py
dblinker/connections/postgres/pool_connection.py
dblinker/connections/postgres/postgres_connection_factory.py
dblinker/connections/sqlite/__init__.py
tests/__init__.py
tests/database_integration_test.py
dblinker-0.0.4.dist-info/LICENSE
dblinker-0.0.4.dist-info/METADATA
dblinker-0.0.4.dist-info/WHEEL
dblinker-0.0.4.dist-info/entry_points.txt
dblinker-0.0.4.dist-info/top_level.txt
dblinker-0.0.4.dist-info/RECORD
