Metadata-Version: 2.1
Name: dblinker
Version: 0.0.4
Summary: A tool to assist with database connections and manage data.
Author-email: Good Boy <pythonic@rexbytes.com>
License: MIT License
Project-URL: Homepage, https://github.com/RexBytes/dblinker
Project-URL: Bug Tracker, https://github.com/RexBytes/dblinker
Classifier: Programming Language :: Python :: 3
Classifier: Programming Language :: Python :: 3.8
Classifier: Programming Language :: Python :: 3.9
Classifier: Programming Language :: Python :: 3.10
Classifier: License :: OSI Approved :: MIT License
Classifier: Operating System :: OS Independent
Classifier: Topic :: Database
Classifier: Topic :: Software Development :: Libraries :: Python Modules
Requires-Python: >=3.8
License-File: LICENSE
